xiaokang/ChangYing.py
xiaokang/__init__.py
xiaokang/sqlite.py
xiaokang-25.3.26.10.38.dist-info/licenses/LICENSE
xiaokang-25.3.26.10.38.dist-info/METADATA
xiaokang-25.3.26.10.38.dist-info/WHEEL
xiaokang-25.3.26.10.38.dist-info/top_level.txt
xiaokang-25.3.26.10.38.dist-info/RECORD
